goppai/__init__.py
goppai/__main__.py
goppai/go2048/__init__.py
goppai/go2048/board.py
goppai/go2048/game.py
goppai/go2048/tile.py
goppai-0.0.1.dist-info/entry_points.txt
goppai-0.0.1.dist-info/LICENSE
goppai-0.0.1.dist-info/WHEEL
goppai-0.0.1.dist-info/METADATA
goppai-0.0.1.dist-info/RECORD
