Metadata-Version: 2.1
Name: goppai
Version: 0.0.1
Summary: Game set for developers to release stress with their console
Keywords: goppai,puzzle,game,cui,2048
Author-email: Prosperokay <prosperokay@gmail.com>
Requires-Python: >=3.8
Classifier: Programming Language :: Python :: 3
Classifier: License :: OSI Approved :: MIT License
Classifier: Operating System :: OS Independent
Requires-Dist: pytest ; extra == "dev"
Requires-Dist: pylint ; extra == "dev"
Requires-Dist: mypy ; extra == "dev"
Requires-Dist: flit ; extra == "dev"
Project-URL: Homepage, https://github.com/ProsperoKay/goppai
Provides-Extra: dev
